swarmauri_crypto_composite/CompositeCrypto.py
swarmauri_crypto_composite/__init__.py
swarmauri_crypto_composite-0.2.0.dev4.dist-info/LICENSE
swarmauri_crypto_composite-0.2.0.dev4.dist-info/METADATA
swarmauri_crypto_composite-0.2.0.dev4.dist-info/WHEEL
swarmauri_crypto_composite-0.2.0.dev4.dist-info/entry_points.txt
swarmauri_crypto_composite-0.2.0.dev4.dist-info/RECORD
